{"MRData":{"xmlns":"","series":"f1","url":"http://api.jolpi.ca/ergast/f1/drivers/raby/results.json","limit":"100","offset":"0","total":"7","RaceTable":{"driverId":"raby","Races":[{"season":"1963","round":"5","url":"https://en.wikipedia.org/wiki/1963_British_Grand_Prix","raceName":"British Grand Prix","Circuit":{"circuitId":"silverstone","url":"https://en.wikipedia.org/wiki/Silverstone_Circuit","circuitName":"Silverstone Circuit","Location":{"lat":"52.0786","long":"-1.01694","locality":"Silverstone","country":"UK"}},"date":"1963-07-20","Results":[{"number":"26","position":"17","positionText":"R","points":"0","Driver":{"driverId":"raby","url":"http://en.wikipedia.org/wiki/Ian_Raby","givenName":"Ian","familyName":"Raby","dateOfBirth":"1921-09-22","nationality":"British"},"Constructor":{"constructorId":"gilby","url":"http://en.wikipedia.org/wiki/Gilby","name":"Gilby","nationality":"British"},"grid":"19","laps":"59","status":"Gearbox"}]},{"season":"1963","round":"6","url":"https://en.wikipedia.org/wiki/1963_German_Grand_Prix","raceName":"German Grand Prix","Circuit":{"circuitId":"nurburgring","url":"https://en.wikipedia.org/wiki/N%C3%BCrburgring","circuitName":"N端rburgring","Location":{"lat":"50.3356","long":"6.9475","locality":"N端rburg","country":"Germany"}},"date":"1963-08-04","Results":[{"number":"25","position":"24","positionText":"F","points":"0","Driver":{"driverId":"raby","url":"http://en.wikipedia.org/wiki/Ian_Raby","givenName":"Ian","familyName":"Raby","dateOfBirth":"1921-09-22","nationality":"British"},"Constructor":{"constructorId":"gilby","url":"http://en.wikipedia.org/wiki/Gilby","name":"Gilby","nationality":"British"},"grid":"0","laps":"0","status":"Did not qualify"}]},{"season":"1963","round":"7","url":"https://en.wikipedia.org/wiki/1963_Italian_Grand_Prix","raceName":"Italian Grand Prix","Circuit":{"circuitId":"monza","url":"https://en.wikipedia.org/wiki/Monza_Circuit","circuitName":"Autodromo Nazionale di Monza","Location":{"lat":"45.615599999999986","long":"9.28111","locality":"Monza","country":"Italy"}},"date":"1963-09-08","Results":[{"number":"50","position":"23","positionText":"F","points":"0","Driver":{"driverId":"raby","url":"http://en.wikipedia.org/wiki/Ian_Raby","givenName":"Ian","familyName":"Raby","dateOfBirth":"1921-09-22","nationality":"British"},"Constructor":{"constructorId":"gilby","url":"http://en.wikipedia.org/wiki/Gilby","name":"Gilby","nationality":"British"},"grid":"0","laps":"0","status":"Did not qualify"}]},{"season":"1964","round":"5","url":"https://en.wikipedia.org/wiki/1964_British_Grand_Prix","raceName":"British Grand Prix","Circuit":{"circuitId":"brands_hatch","url":"https://en.wikipedia.org/wiki/Brands_Hatch","circuitName":"Brands Hatch","Location":{"lat":"51.3569","long":"0.263056","locality":"Kent","country":"UK"}},"date":"1964-07-11","Results":[{"number":"23","position":"18","positionText":"R","points":"0","Driver":{"driverId":"raby","url":"http://en.wikipedia.org/wiki/Ian_Raby","givenName":"Ian","familyName":"Raby","dateOfBirth":"1921-09-22","nationality":"British"},"Constructor":{"constructorId":"brabham-brm","url":"http://en.wikipedia.org/wiki/Brabham","name":"Brabham-BRM","nationality":"British"},"grid":"23","laps":"37","status":"Accident"}]},{"season":"1964","round":"8","url":"https://en.wikipedia.org/wiki/1964_Italian_Grand_Prix","raceName":"Italian Grand Prix","Circuit":{"circuitId":"monza","url":"https://en.wikipedia.org/wiki/Monza_Circuit","circuitName":"Autodromo Nazionale di Monza","Location":{"lat":"45.615599999999986","long":"9.28111","locality":"Monza","country":"Italy"}},"date":"1964-09-06","Results":[{"number":"56","position":"24","positionText":"F","points":"0","Driver":{"driverId":"raby","url":"http://en.wikipedia.org/wiki/Ian_Raby","givenName":"Ian","familyName":"Raby","dateOfBirth":"1921-09-22","nationality":"British"},"Constructor":{"constructorId":"brabham-brm","url":"http://en.wikipedia.org/wiki/Brabham","name":"Brabham-BRM","nationality":"British"},"grid":"0","laps":"0","status":"Did not qualify"}]},{"season":"1965","round":"5","url":"https://en.wikipedia.org/wiki/1965_British_Grand_Prix","raceName":"British Grand Prix","Circuit":{"circuitId":"silverstone","url":"https://en.wikipedia.org/wiki/Silverstone_Circuit","circuitName":"Silverstone Circuit","Location":{"lat":"52.0786","long":"-1.01694","locality":"Silverstone","country":"UK"}},"date":"1965-07-10","Results":[{"number":"24","position":"11","positionText":"11","points":"0","Driver":{"driverId":"raby","url":"http://en.wikipedia.org/wiki/Ian_Raby","givenName":"Ian","familyName":"Raby","dateOfBirth":"1921-09-22","nationality":"British"},"Constructor":{"constructorId":"brabham-brm","url":"http://en.wikipedia.org/wiki/Brabham","name":"Brabham-BRM","nationality":"British"},"grid":"20","laps":"73","status":"+7 Laps"}]},{"season":"1965","round":"7","url":"https://en.wikipedia.org/wiki/1965_German_Grand_Prix","raceName":"German Grand Prix","Circuit":{"circuitId":"nurburgring","url":"https://en.wikipedia.org/wiki/N%C3%BCrburgring","circuitName":"N端rburgring","Location":{"lat":"50.3356","long":"6.9475","locality":"N端rburg","country":"Germany"}},"date":"1965-08-01","Results":[{"number":"23","position":"21","positionText":"F","points":"0","Driver":{"driverId":"raby","url":"http://en.wikipedia.org/wiki/Ian_Raby","givenName":"Ian","familyName":"Raby","dateOfBirth":"1921-09-22","nationality":"British"},"Constructor":{"constructorId":"brabham-climax","url":"http://en.wikipedia.org/wiki/Brabham","name":"Brabham-Climax","nationality":"British"},"grid":"0","laps":"0","status":"Did not qualify"}]}]}}}