{"MRData":{"xmlns":"","series":"f1","url":"http://api.jolpi.ca/ergast/f1/drivers/seidel/results.json","limit":"100","offset":"0","total":"13","RaceTable":{"driverId":"seidel","Races":[{"season":"1953","round":"7","url":"https://en.wikipedia.org/wiki/1953_German_Grand_Prix","raceName":"German Grand Prix","Circuit":{"circuitId":"nurburgring","url":"https://en.wikipedia.org/wiki/N%C3%BCrburgring","circuitName":"Nürburgring","Location":{"lat":"50.3356","long":"6.9475","locality":"Nürburg","country":"Germany"}},"date":"1953-08-02","Results":[{"number":"22","position":"16","positionText":"16","points":"0","Driver":{"driverId":"seidel","url":"http://en.wikipedia.org/wiki/Wolfgang_Seidel","givenName":"Wolfgang","familyName":"Seidel","dateOfBirth":"1926-07-04","nationality":"German"},"Constructor":{"constructorId":"veritas","url":"http://en.wikipedia.org/wiki/Veritas_(constructor)","name":"Veritas","nationality":"German"},"grid":"29","laps":"14","status":"+4 Laps"}]},{"season":"1958","round":"5","url":"https://en.wikipedia.org/wiki/1958_Belgian_Grand_Prix","raceName":"Belgian Grand Prix","Circuit":{"circuitId":"spa","url":"https://en.wikipedia.org/wiki/Circuit_de_Spa-Francorchamps","circuitName":"Circuit de Spa-Francorchamps","Location":{"lat":"50.4372","long":"5.97139","locality":"Spa","country":"Belgium"}},"date":"1958-06-15","Results":[{"number":"32","position":"17","positionText":"R","points":"0","Driver":{"driverId":"seidel","url":"http://en.wikipedia.org/wiki/Wolfgang_Seidel","givenName":"Wolfgang","familyName":"Seidel","dateOfBirth":"1926-07-04","nationality":"German"},"Constructor":{"constructorId":"maserati","url":"http://en.wikipedia.org/wiki/Maserati","name":"Maserati","nationality":"Italian"},"grid":"17","laps":"4","status":"Halfshaft"}]},{"season":"1958","round":"8","url":"https://en.wikipedia.org/wiki/1958_German_Grand_Prix","raceName":"German Grand Prix","Circuit":{"circuitId":"nurburgring","url":"https://en.wikipedia.org/wiki/N%C3%BCrburgring","circuitName":"Nürburgring","Location":{"lat":"50.3356","long":"6.9475","locality":"Nürburg","country":"Germany"}},"date":"1958-08-03","Results":[{"number":"22","position":"14","positionText":"R","points":"0","Driver":{"driverId":"seidel","url":"http://en.wikipedia.org/wiki/Wolfgang_Seidel","givenName":"Wolfgang","familyName":"Seidel","dateOfBirth":"1926-07-04","nationality":"German"},"Constructor":{"constructorId":"cooper","url":"http://en.wikipedia.org/wiki/Cooper_Car_Company","name":"Cooper","nationality":"British"},"grid":"17","laps":"9","status":"Suspension"}]},{"season":"1958","round":"11","url":"https://en.wikipedia.org/wiki/1958_Moroccan_Grand_Prix","raceName":"Moroccan Grand Prix","Circuit":{"circuitId":"ain-diab","url":"https://en.wikipedia.org/wiki/Ain-Diab_Circuit","circuitName":"Ain Diab","Location":{"lat":"33.5786","long":"-7.6875","locality":"Casablanca","country":"Morocco"}},"date":"1958-10-19","Results":[{"number":"24","position":"23","positionText":"R","points":"0","Driver":{"driverId":"seidel","url":"http://en.wikipedia.org/wiki/Wolfgang_Seidel","givenName":"Wolfgang","familyName":"Seidel","dateOfBirth":"1926-07-04","nationality":"German"},"Constructor":{"constructorId":"cooper","url":"http://en.wikipedia.org/wiki/Cooper_Car_Company","name":"Cooper","nationality":"British"},"grid":"20","laps":"15","status":"Accident"}]},{"season":"1960","round":"9","url":"https://en.wikipedia.org/wiki/1960_Italian_Grand_Prix","raceName":"Italian Grand Prix","Circuit":{"circuitId":"monza","url":"https://en.wikipedia.org/wiki/Monza_Circuit","circuitName":"Autodromo Nazionale di Monza","Location":{"lat":"45.615599999999986","long":"9.28111","locality":"Monza","country":"Italy"}},"date":"1960-09-04","Results":[{"number":"10","position":"9","positionText":"9","points":"0","Driver":{"driverId":"seidel","url":"http://en.wikipedia.org/wiki/Wolfgang_Seidel","givenName":"Wolfgang","familyName":"Seidel","dateOfBirth":"1926-07-04","nationality":"German"},"Constructor":{"constructorId":"cooper-climax","url":"http://en.wikipedia.org/wiki/Cooper_Car_Company","name":"Cooper-Climax","nationality":"British"},"grid":"13","laps":"44","status":"+6 Laps"}]},{"season":"1961","round":"3","url":"https://en.wikipedia.org/wiki/1961_Belgian_Grand_Prix","raceName":"Belgian Grand Prix","Circuit":{"circuitId":"spa","url":"https://en.wikipedia.org/wiki/Circuit_de_Spa-Francorchamps","circuitName":"Circuit de Spa-Francorchamps","Location":{"lat":"50.4372","long":"5.97139","locality":"Spa","country":"Belgium"}},"date":"1961-06-18","Results":[{"number":"48","position":"23","positionText":"W","points":"0","Driver":{"driverId":"seidel","url":"http://en.wikipedia.org/wiki/Wolfgang_Seidel","givenName":"Wolfgang","familyName":"Seidel","dateOfBirth":"1926-07-04","nationality":"German"},"Constructor":{"constructorId":"lotus-climax","url":"http://en.wikipedia.org/wiki/Team_Lotus","name":"Lotus-Climax","nationality":"British"},"grid":"0","laps":"0","status":"Withdrew"}]},{"season":"1961","round":"4","url":"https://en.wikipedia.org/wiki/1961_French_Grand_Prix","raceName":"French Grand Prix","Circuit":{"circuitId":"reims","url":"https://en.wikipedia.org/wiki/Reims-Gueux","circuitName":"Reims-Gueux","Location":{"lat":"49.2542","long":"3.93083","locality":"Reims","country":"France"}},"date":"1961-07-02","Results":[{"number":"46","position":"27","positionText":"W","points":"0","Driver":{"driverId":"seidel","url":"http://en.wikipedia.org/wiki/Wolfgang_Seidel","givenName":"Wolfgang","familyName":"Seidel","dateOfBirth":"1926-07-04","nationality":"German"},"Constructor":{"constructorId":"lotus-climax","url":"http://en.wikipedia.org/wiki/Team_Lotus","name":"Lotus-Climax","nationality":"British"},"grid":"0","laps":"0","status":"Withdrew"}]},{"season":"1961","round":"5","url":"https://en.wikipedia.org/wiki/1961_British_Grand_Prix","raceName":"British Grand Prix","Circuit":{"circuitId":"aintree","url":"https://en.wikipedia.org/wiki/Aintree_Motor_Racing_Circuit","circuitName":"Aintree","Location":{"lat":"53.4769","long":"-2.94056","locality":"Liverpool","country":"UK"}},"date":"1961-07-15","Results":[{"number":"52","position":"17","positionText":"17","points":"0","Driver":{"driverId":"seidel","url":"http://en.wikipedia.org/wiki/Wolfgang_Seidel","givenName":"Wolfgang","familyName":"Seidel","dateOfBirth":"1926-07-04","nationality":"German"},"Constructor":{"constructorId":"lotus-climax","url":"http://en.wikipedia.org/wiki/Team_Lotus","name":"Lotus-Climax","nationality":"British"},"grid":"22","laps":"58","status":"+17 Laps"}]},{"season":"1961","round":"6","url":"https://en.wikipedia.org/wiki/1961_German_Grand_Prix","raceName":"German Grand Prix","Circuit":{"circuitId":"nurburgring","url":"https://en.wikipedia.org/wiki/N%C3%BCrburgring","circuitName":"Nürburgring","Location":{"lat":"50.3356","long":"6.9475","locality":"Nürburg","country":"Germany"}},"date":"1961-08-06","Results":[{"number":"26","position":"23","positionText":"R","points":"0","Driver":{"driverId":"seidel","url":"http://en.wikipedia.org/wiki/Wolfgang_Seidel","givenName":"Wolfgang","familyName":"Seidel","dateOfBirth":"1926-07-04","nationality":"German"},"Constructor":{"constructorId":"lotus-climax","url":"http://en.wikipedia.org/wiki/Team_Lotus","name":"Lotus-Climax","nationality":"British"},"grid":"23","laps":"3","status":"Handling"}]},{"season":"1961","round":"7","url":"https://en.wikipedia.org/wiki/1961_Italian_Grand_Prix","raceName":"Italian Grand Prix","Circuit":{"circuitId":"monza","url":"https://en.wikipedia.org/wiki/Monza_Circuit","circuitName":"Autodromo Nazionale di Monza","Location":{"lat":"45.615599999999986","long":"9.28111","locality":"Monza","country":"Italy"}},"date":"1961-09-10","Results":[{"number":"56","position":"30","positionText":"R","points":"0","Driver":{"driverId":"seidel","url":"http://en.wikipedia.org/wiki/Wolfgang_Seidel","givenName":"Wolfgang","familyName":"Seidel","dateOfBirth":"1926-07-04","nationality":"German"},"Constructor":{"constructorId":"lotus-climax","url":"http://en.wikipedia.org/wiki/Team_Lotus","name":"Lotus-Climax","nationality":"British"},"grid":"28","laps":"1","status":"Engine"}]},{"season":"1962","round":"1","url":"https://en.wikipedia.org/wiki/1962_Dutch_Grand_Prix","raceName":"Dutch Grand Prix","Circuit":{"circuitId":"zandvoort","url":"https://en.wikipedia.org/wiki/Circuit_Zandvoort","circuitName":"Circuit Park Zandvoort","Location":{"lat":"52.3888","long":"4.54092","locality":"Zandvoort","country":"Netherlands"}},"date":"1962-05-20","Results":[{"number":"16","position":"14","positionText":"R","points":"0","Driver":{"driverId":"seidel","url":"http://en.wikipedia.org/wiki/Wolfgang_Seidel","givenName":"Wolfgang","familyName":"Seidel","dateOfBirth":"1926-07-04","nationality":"German"},"Constructor":{"constructorId":"emeryson","url":"http://en.wikipedia.org/wiki/Emeryson","name":"Emeryson","nationality":"British"},"grid":"20","laps":"52","status":"Not classified"}]},{"season":"1962","round":"5","url":"https://en.wikipedia.org/wiki/1962_British_Grand_Prix","raceName":"British Grand Prix","Circuit":{"circuitId":"aintree","url":"https://en.wikipedia.org/wiki/Aintree_Motor_Racing_Circuit","circuitName":"Aintree","Location":{"lat":"53.4769","long":"-2.94056","locality":"Liverpool","country":"UK"}},"date":"1962-07-21","Results":[{"number":"44","position":"20","positionText":"R","points":"0","Driver":{"driverId":"seidel","url":"http://en.wikipedia.org/wiki/Wolfgang_Seidel","givenName":"Wolfgang","familyName":"Seidel","dateOfBirth":"1926-07-04","nationality":"German"},"Constructor":{"constructorId":"lotus-brm","url":"http://en.wikipedia.org/wiki/Team_Lotus","name":"Lotus-BRM","nationality":"British"},"grid":"21","laps":"11","status":"Brakes"}]},{"season":"1962","round":"6","url":"https://en.wikipedia.org/wiki/1962_German_Grand_Prix","raceName":"German Grand Prix","Circuit":{"circuitId":"nurburgring","url":"https://en.wikipedia.org/wiki/N%C3%BCrburgring","circuitName":"Nürburgring","Location":{"lat":"50.3356","long":"6.9475","locality":"Nürburg","country":"Germany"}},"date":"1962-08-05","Results":[{"number":"34","position":"28","positionText":"F","points":"0","Driver":{"driverId":"seidel","url":"http://en.wikipedia.org/wiki/Wolfgang_Seidel","givenName":"Wolfgang","familyName":"Seidel","dateOfBirth":"1926-07-04","nationality":"German"},"Constructor":{"constructorId":"lotus-brm","url":"http://en.wikipedia.org/wiki/Team_Lotus","name":"Lotus-BRM","nationality":"British"},"grid":"0","laps":"0","status":"Did not qualify"}]}]}}}