{"MRData":{"xmlns":"","series":"f1","url":"http://api.jolpi.ca/ergast/f1/drivers/takahara/results.json","limit":"100","offset":"0","total":"2","RaceTable":{"driverId":"takahara","Races":[{"season":"1976","round":"16","url":"https://en.wikipedia.org/wiki/1976_Japanese_Grand_Prix","raceName":"Japanese Grand Prix","Circuit":{"circuitId":"fuji","url":"https://en.wikipedia.org/wiki/Fuji_Speedway","circuitName":"Fuji Speedway","Location":{"lat":"35.3717","long":"138.927","locality":"Oyama","country":"Japan"}},"date":"1976-10-24","Results":[{"number":"18","position":"9","positionText":"9","points":"0","Driver":{"driverId":"takahara","url":"http://en.wikipedia.org/wiki/Noritake_Takahara","givenName":"Noritake","familyName":"Takahara","dateOfBirth":"1951-06-06","nationality":"Japanese"},"Constructor":{"constructorId":"surtees","url":"http://en.wikipedia.org/wiki/Surtees","name":"Surtees","nationality":"British"},"grid":"24","laps":"70","status":"+3 Laps"}]},{"season":"1977","round":"17","url":"https://en.wikipedia.org/wiki/1977_Japanese_Grand_Prix","raceName":"Japanese Grand Prix","Circuit":{"circuitId":"fuji","url":"https://en.wikipedia.org/wiki/Fuji_Speedway","circuitName":"Fuji Speedway","Location":{"lat":"35.3717","long":"138.927","locality":"Oyama","country":"Japan"}},"date":"1977-10-23","Results":[{"number":"51","position":"22","positionText":"R","points":"0","Driver":{"driverId":"takahara","url":"http://en.wikipedia.org/wiki/Noritake_Takahara","givenName":"Noritake","familyName":"Takahara","dateOfBirth":"1951-06-06","nationality":"Japanese"},"Constructor":{"constructorId":"kojima","url":"http://en.wikipedia.org/wiki/Kojima_Engineering","name":"Kojima","nationality":"Japanese"},"grid":"19","laps":"1","status":"Collision"}]}]}}}